setup.cfg
setup.py
LFUCache.egg-info/PKG-INFO
LFUCache.egg-info/SOURCES.txt
LFUCache.egg-info/dependency_links.txt
LFUCache.egg-info/top_level.txt
lfucache/__init__.py
lfucache/lfu_cache.py